CHANGES.rst
DESCRIPTION.rst
LICENSE
MANIFEST.in
README.md
setup.py
src/wai.annotations.generic.egg-info/PKG-INFO
src/wai.annotations.generic.egg-info/SOURCES.txt
src/wai.annotations.generic.egg-info/dependency_links.txt
src/wai.annotations.generic.egg-info/entry_points.txt
src/wai.annotations.generic.egg-info/namespace_packages.txt
src/wai.annotations.generic.egg-info/requires.txt
src/wai.annotations.generic.egg-info/top_level.txt
src/wai/annotations/generic/__init__.py
src/wai/annotations/generic/core/__init__.py
src/wai/annotations/generic/core/_utils.py
src/wai/annotations/generic/isp/__init__.py
src/wai/annotations/generic/isp/audio_classification/__init__.py
src/wai/annotations/generic/isp/audio_classification/specifier/_AudioClassificationISPSpecifier.py
src/wai/annotations/generic/isp/audio_classification/specifier/__init__.py
src/wai/annotations/generic/isp/audio_classification/test/_TestAC.py
src/wai/annotations/generic/isp/audio_classification/test/__init__.py
src/wai/annotations/generic/isp/base/__init__.py
src/wai/annotations/generic/isp/base/component/_BaseISP.py
src/wai/annotations/generic/isp/base/component/__init__.py
src/wai/annotations/generic/isp/image_classification/__init__.py
src/wai/annotations/generic/isp/image_classification/specifier/_ImageClassificationISPSpecifier.py
src/wai/annotations/generic/isp/image_classification/specifier/__init__.py
src/wai/annotations/generic/isp/image_classification/test/_TestIC.py
src/wai/annotations/generic/isp/image_classification/test/__init__.py
src/wai/annotations/generic/isp/image_segmentation/__init__.py
src/wai/annotations/generic/isp/image_segmentation/specifier/_ImageSegmentationISPSpecifier.py
src/wai/annotations/generic/isp/image_segmentation/specifier/__init__.py
src/wai/annotations/generic/isp/image_segmentation/test/_TestIS.py
src/wai/annotations/generic/isp/image_segmentation/test/__init__.py
src/wai/annotations/generic/isp/object_detection/__init__.py
src/wai/annotations/generic/isp/object_detection/specifier/_ObjectDetectionISPSpecifier.py
src/wai/annotations/generic/isp/object_detection/specifier/__init__.py
src/wai/annotations/generic/isp/object_detection/test/_TestOD.py
src/wai/annotations/generic/isp/object_detection/test/__init__.py
src/wai/annotations/generic/isp/spectrum_classification/__init__.py
