Metadata-Version: 2.1
Name: wai.annotations.generic
Version: 1.1.0
Summary: Module with generic plugins for wai.annotations that use user specified classes.
Home-page: https://github.com/waikato-datamining/wai-annotations-generic
Author: Peter Reutemann
Author-email: fracpete@waikato.ac.nz
License: Apache License Version 2.0
Platform: UNKNOWN
Classifier: Development Status :: 4 - Beta
Classifier: License :: OSI Approved :: Apache Software License
Classifier: Topic :: Scientific/Engineering :: Mathematics
Classifier: Programming Language :: Python :: 3
License-File: LICENSE
